nonebot_plugin_vvquest/__init__.py
nonebot_plugin_vvquest/config.py
nonebot_plugin_vvquest-0.1.0.dist-info/licenses/LICENSE
nonebot_plugin_vvquest-0.1.0.dist-info/METADATA
nonebot_plugin_vvquest-0.1.0.dist-info/WHEEL
nonebot_plugin_vvquest-0.1.0.dist-info/top_level.txt
nonebot_plugin_vvquest-0.1.0.dist-info/RECORD
