Metadata-Version: 2.4
Name: nonebot-plugin-vvquest
Version: 0.1.0
Summary: 通过API获取维维语录图片的NoneBot2插件
Author-email: webjoin111 <455457521@qq.com>
License: MIT
Project-URL: Homepage, https://github.com/webjoin111/nonebot-plugin-vvquest
Project-URL: Repository, https://github.com/webjoin111/nonebot-plugin-vvquest
Project-URL: Issues, https://github.com/webjoin111/nonebot-plugin-vvquest/issues
Classifier: License :: OSI Approved :: MIT License
Classifier: Programming Language :: Python
Classifier: Programming Language :: Python :: 3
Classifier: Programming Language :: Python :: 3.8
Classifier: Programming Language :: Python :: 3.9
Classifier: Programming Language :: Python :: 3.10
Classifier: Programming Language :: Python :: 3.11
Classifier: Operating System :: OS Independent
Requires-Python: >=3.8
License-File: LICENSE
Requires-Dist: nonebot2>=2.3.0
Requires-Dist: nonebot-adapter-onebot>=2.0.0
Requires-Dist: httpx<1.0.0,>=0.20.0
Dynamic: license-file
